[{"kind": "Listing", "data": {"after": null, "dist": 1, "modhash": "", "geo_filter": "", "children": [{"kind": "t3", "data": {"approved_at_utc": null, "subreddit": "castaneda", "selftext": "I read somebody say this was a Castaneda theory and it puzzled me, I don't know much about this topic though and haven't read enough so that's why I'm asking", "user_reports": [], "saved": false, "mod_reason_title": null, "gilded": 0, "clicked": false, "title": "Is it true that dreaming in a dream means you're shifting dimensions/realities?", "link_flair_richtext": [{"e": "text", "t": "Dreaming"}], "subreddit_name_prefixed": "r/castaneda", "hidden": false, "pwls": 7, "link_flair_css_class": "", "downs": 0, "thumbnail_height": null, "top_awarded_type": null, "parent_whitelist_status": "some_ads", "hide_score": false, "name": "t3_xx9b4l", "quarantine": false, "link_flair_text_color": "light", "upvote_ratio": 0.89, "author_flair_background_color": null, "subreddit_type": "public", "ups": 7, "total_awards_received": 0, "media_embed": {}, "thumbnail_width": null, "author_flair_template_id": null, "is_original_content": false, "author_fullname": "t2_qabab23e", "secure_media": null, "is_reddit_media_domain": false, "is_meta": false, "category": null, "secure_media_embed": {}, "link_flair_text": "Dreaming", "can_mod_post": false, "score": 7, "approved_by": null, "is_created_from_ads_ui": false, "author_premium": false, "thumbnail": "self", "edited": false, "author_flair_css_class": null, "author_flair_richtext": [], "gildings": {}, "content_categories": null, "is_self": true, "mod_note": null, "created": 1665073180.0, "link_flair_type": "richtext", "wls": 7, "removed_by_category": null, "banned_by": null, "author_flair_type": "text", "domain": "self.castaneda", "allow_live_comments": false, "selftext_html": "&lt;!-- SC_OFF --&gt;&lt;div class=\"md\"&gt;&lt;p&gt;I read somebody say this was a Castaneda theory and it puzzled me, I don&amp;#39;t know much about this topic though and haven&amp;#39;t read enough so that&amp;#39;s why I&amp;#39;m asking&lt;/p&gt;\n&lt;/div&gt;&lt;!-- SC_ON --&gt;", "likes": null, "suggested_sort": null, "banned_at_utc": null, "view_count": null, "archived": false, "no_follow": false, "is_crosspostable": false, "pinned": false, "over_18": false, "all_awardings": [], "awarders": [], "media_only": false, "link_flair_template_id": "d442824c-6005-11ea-b1ec-0ebd57ae4429", "can_gild": false, "spoiler": false, "locked": false, "author_flair_text": null, "treatment_tags": [], "visited": false, "removed_by": null, "num_reports": null, "distinguished": null, "subreddit_id": "t5_2sblm", "author_is_blocked": false, "mod_reason_by": null, "removal_reason": null, "link_flair_background_color": "#373c3f", "id": "xx9b4l", "is_robot_indexable": true, "num_duplicates": 0, "report_reasons": null, "author": "ermac_95", "discussion_type": null, "num_comments": 5, "send_replies": true, "media": null, "contest_mode": false, "author_patreon_flair": false, "author_flair_text_color": null, "permalink": "/r/castaneda/comments/xx9b4l/is_it_true_that_dreaming_in_a_dream_means_youre/", "whitelist_status": "some_ads", "stickied": false, "url": "https://www.reddit.com/r/castaneda/comments/xx9b4l/is_it_true_that_dreaming_in_a_dream_means_youre/", "subreddit_subscribers": 9561, "created_utc": 1665073180.0, "num_crossposts": 0, "mod_reports": [], "is_video": false}}], "before": null}}, {"kind": "Listing", "data": {"after": null, "dist": null, "modhash": "", "geo_filter": "", "children": [{"kind": "t1", "data": {"subreddit_id": "t5_2sblm", "approved_at_utc": null, "author_is_blocked": false, "comment_type": null, "awarders": [], "mod_reason_by": null, "banned_by": null, "author_flair_type": "text", "total_awards_received": 0, "subreddit": "castaneda", "author_flair_template_id": null, "likes": null, "replies": {"kind": "Listing", "data": {"after": null, "dist": null, "modhash": "", "geo_filter": "", "children": [{"kind": "t1", "data": {"subreddit_id": "t5_2sblm", "approved_at_utc": null, "author_is_blocked": false, "comment_type": null, "awarders": [], "mod_reason_by": null, "banned_by": null, "author_flair_type": "text", "total_awards_received": 0, "subreddit": "castaneda", "author_flair_template_id": null, "likes": null, "replies": {"kind": "Listing", "data": {"after": null, "dist": null, "modhash": "", "geo_filter": "", "children": [{"kind": "t1", "data": {"subreddit_id": "t5_2sblm", "approved_at_utc": null, "author_is_blocked": false, "comment_type": null, "awarders": [], "mod_reason_by": null, "banned_by": null, "author_flair_type": "text", "total_awards_received": 0, "subreddit": "castaneda", "author_flair_template_id": null, "likes": null, "replies": {"kind": "Listing", "data": {"after": null, "dist": null, "modhash": "", "geo_filter": "", "children": [{"kind": "t1", "data": {"total_awards_received": 0, "approved_at_utc": null, "author_is_blocked": false, "comment_type": null, "awarders": [], "mod_reason_by": null, "banned_by": null, "ups": -1, "removal_reason": null, "link_id": "t3_xx9b4l", "author_flair_template_id": null, "likes": null, "replies": {"kind": "Listing", "data": {"after": null, "dist": null, "modhash": "", "geo_filter": "", "children": [{"kind": "t1", "data": {"subreddit_id": "t5_2sblm", "approved_at_utc": null, "author_is_blocked": false, "comment_type": null, "awarders": [], "mod_reason_by": null, "banned_by": null, "author_flair_type": "text", "total_awards_received": 0, "subreddit": "castaneda", "author_flair_template_id": null, "distinguished": null, "likes": null, "replies": {"kind": "Listing", "data": {"after": null, "dist": null, "modhash": "", "geo_filter": "", "children": [{"kind": "t1", "data": {"total_awards_received": 0, "approved_at_utc": null, "author_is_blocked": false, "comment_type": null, "awarders": [], "mod_reason_by": null, "banned_by": null, "ups": 0, "removal_reason": null, "link_id": "t3_xx9b4l", "author_flair_template_id": null, "likes": null, "replies": {"kind": "Listing", "data": {"after": null, "dist": null, "modhash": "", "geo_filter": "", "children": [{"kind": "t1", "data": {"subreddit_id": "t5_2sblm", "approved_at_utc": null, "author_is_blocked": false, "comment_type": null, "awarders": [], "mod_reason_by": null, "banned_by": null, "author_flair_type": "text", "total_awards_received": 0, "subreddit": "castaneda", "author_flair_template_id": null, "distinguished": null, "likes": null, "replies": "", "user_reports": [], "saved": false, "id": "ireiu4n", "banned_at_utc": null, "mod_reason_title": null, "gilded": 0, "archived": false, "collapsed_reason_code": null, "no_follow": false, "author": "danl999", "can_mod_post": false, "send_replies": true, "parent_id": "t1_ircn1hk", "score": 5, "author_fullname": "t2_yicrx32", "approved_by": null, "mod_note": null, "all_awardings": [], "collapsed": false, "body": "Back to your crappy behavior again I see.", "edited": false, "gildings": {}, "author_flair_css_class": null, "name": "t1_ireiu4n", "is_submitter": false, "downs": 0, "author_flair_richtext": [], "author_patreon_flair": false, "body_html": "&lt;div class=\"md\"&gt;&lt;p&gt;Back to your crappy behavior again I see.&lt;/p&gt;\n&lt;/div&gt;", "removal_reason": null, "collapsed_reason": null, "link_id": "t3_xx9b4l", "associated_award": null, "stickied": false, "author_premium": false, "can_gild": false, "top_awarded_type": null, "unrepliable_reason": null, "author_flair_text_color": null, "score_hidden": false, "permalink": "/r/castaneda/comments/xx9b4l/is_it_true_that_dreaming_in_a_dream_means_youre/ireiu4n/", "subreddit_type": "public", "locked": false, "report_reasons": null, "created": 1665149914.0, "author_flair_text": null, "treatment_tags": [], "created_utc": 1665149914.0, "subreddit_name_prefixed": "r/castaneda", "controversiality": 0, "depth": 6, "author_flair_background_color": null, "collapsed_because_crowd_control": null, "mod_reports": [], "num_reports": null, "ups": 5}}], "before": null}}, "user_reports": [], "saved": false, "id": "ircn1hk", "banned_at_utc": null, "mod_reason_title": null, "gilded": 0, "archived": false, "collapsed_reason_code": null, "no_follow": true, "author": "[deleted]", "can_mod_post": false, "created_utc": 1665103643.0, "send_replies": true, "parent_id": "t1_ircll2k", "score": 0, "approved_by": null, "report_reasons": null, "all_awardings": [], "subreddit_id": "t5_2sblm", "body": "[deleted]", "edited": 1665106389.0, "author_flair_css_class": null, "downs": 0, "is_submitter": false, "body_html": "&lt;div class=\"md\"&gt;&lt;p&gt;[deleted]&lt;/p&gt;\n&lt;/div&gt;", "gildings": {}, "collapsed_reason": null, "associated_award": null, "stickied": false, "subreddit_type": "public", "can_gild": false, "top_awarded_type": null, "unrepliable_reason": null, "author_flair_text_color": "dark", "score_hidden": false, "permalink": "/r/castaneda/comments/xx9b4l/is_it_true_that_dreaming_in_a_dream_means_youre/ircn1hk/", "num_reports": null, "locked": false, "name": "t1_ircn1hk", "created": 1665103643.0, "subreddit": "castaneda", "author_flair_text": null, "treatment_tags": [], "collapsed": false, "subreddit_name_prefixed": "r/castaneda", "controversiality": 0, "depth": 5, "author_flair_background_color": "", "collapsed_because_crowd_control": null, "mod_reports": [], "mod_note": null, "distinguished": null}}], "before": null}}, "user_reports": [], "saved": false, "id": "ircll2k", "banned_at_utc": null, "mod_reason_title": null, "gilded": 0, "archived": false, "collapsed_reason_code": null, "no_follow": false, "author": "a-friendly_guy", "can_mod_post": false, "send_replies": true, "parent_id": "t1_irckcmu", "score": 4, "author_fullname": "t2_2mqyjq", "removal_reason": null, "approved_by": null, "mod_note": null, "all_awardings": [], "body": "No risk of the dream ending by waking up out of it against your will.", "edited": false, "author_flair_css_class": null, "name": "t1_ircll2k", "is_submitter": false, "downs": 0, "author_flair_richtext": [], "author_patreon_flair": false, "body_html": "&lt;div class=\"md\"&gt;&lt;p&gt;No risk of the dream ending by waking up out of it against your will.&lt;/p&gt;\n&lt;/div&gt;", "gildings": {}, "collapsed_reason": null, "link_id": "t3_xx9b4l", "associated_award": null, "stickied": false, "author_premium": false, "can_gild": false, "top_awarded_type": null, "unrepliable_reason": null, "author_flair_text_color": null, "treatment_tags": [], "score_hidden": false, "permalink": "/r/castaneda/comments/xx9b4l/is_it_true_that_dreaming_in_a_dream_means_youre/ircll2k/", "subreddit_type": "public", "locked": false, "report_reasons": null, "created": 1665102898.0, "author_flair_text": null, "collapsed": false, "created_utc": 1665102898.0, "subreddit_name_prefixed": "r/castaneda", "controversiality": 0, "depth": 4, "author_flair_background_color": null, "collapsed_because_crowd_control": null, "mod_reports": [], "num_reports": null, "ups": 4}}], "before": null}}, "user_reports": [], "saved": false, "id": "irckcmu", "banned_at_utc": null, "mod_reason_title": null, "gilded": 0, "archived": false, "collapsed_reason_code": null, "no_follow": true, "author": "[deleted]", "can_mod_post": false, "send_replies": true, "parent_id": "t1_irayhsv", "score": -1, "approved_by": null, "report_reasons": null, "all_awardings": [], "subreddit_id": "t5_2sblm", "body": "[deleted]", "edited": false, "downs": 0, "author_flair_css_class": null, "collapsed": false, "is_submitter": false, "body_html": "&lt;div class=\"md\"&gt;&lt;p&gt;[deleted]&lt;/p&gt;\n&lt;/div&gt;", "gildings": {}, "collapsed_reason": null, "associated_award": null, "stickied": false, "subreddit_type": "public", "can_gild": false, "top_awarded_type": null, "unrepliable_reason": null, "author_flair_text_color": "dark", "score_hidden": false, "permalink": "/r/castaneda/comments/xx9b4l/is_it_true_that_dreaming_in_a_dream_means_youre/irckcmu/", "num_reports": null, "locked": false, "name": "t1_irckcmu", "created": 1665102249.0, "subreddit": "castaneda", "author_flair_text": null, "treatment_tags": [], "created_utc": 1665102249.0, "subreddit_name_prefixed": "r/castaneda", "controversiality": 0, "depth": 3, "author_flair_background_color": "", "collapsed_because_crowd_control": null, "mod_reports": [], "mod_note": null, "distinguished": null}}], "before": null}}, "user_reports": [], "saved": false, "id": "irayhsv", "banned_at_utc": null, "mod_reason_title": null, "gilded": 0, "archived": false, "collapsed_reason_code": null, "no_follow": false, "author": "danl999", "can_mod_post": false, "send_replies": true, "parent_id": "t1_irawxb6", "score": 13, "author_fullname": "t2_yicrx32", "removal_reason": null, "approved_by": null, "mod_note": null, "all_awardings": [], "body": "Wow, somewhat sincere.\n\nYou've been confused by the Lucid Dreaming folks, who toss me out if I try to teach them how to do waking dreaming.\n\nYou'd think they'd go NUTS to hear they can do lucid dreaming 3 hours every single day, with no risk of losing lucidity, and no risk of waking up.\n\nBut it only makes them so angry, they delete my posts.\n\nThose are bad men in that subreddit, so I gave up on them.  God only knows what they're really after.\n\nIt's not exploration of dreams.\n\nThe pictures you see in here are mostly done fully awake, sober, eyes open, and kick the butt of anyone in the lucid dreaming forum, 100000 times over.\n\nIt's real magic, from 10,000 year old proto-siberian shamanism.\n\nIt got handed down through the Olmecs.\n\nShapeshifting was their favorite dreaming hobby.\n\nIs that a \"shifted reality\"?  When you turn into a Jaguar for real?\n\nBeats me, but you seem to be polluted with fake system narratives so it's not going to be easy for you to accept.\n\n[https://www.google.com/search?q=olmec+shamanism+werejaguar&amp;rlz=1C1CHZL\\_enUS706US706&amp;source=lnms&amp;tbm=isch&amp;sa=X&amp;ved=2ahUKEwiH-\\_-Yi8z6AhXoL0QIHXaXB80Q\\_AUoAXoECAEQAw&amp;biw=1041&amp;bih=774&amp;dpr=1.25](https://www.google.com/search?q=olmec+shamanism+werejaguar&amp;rlz=1C1CHZL_enUS706US706&amp;source=lnms&amp;tbm=isch&amp;sa=X&amp;ved=2ahUKEwiH-_-Yi8z6AhXoL0QIHXaXB80Q_AUoAXoECAEQAw&amp;biw=1041&amp;bih=774&amp;dpr=1.25)\n\nHopefully the man holding himself in his dream form is at the top.\n\nBut if not, scroll down in this wikipedia entry and you'll find him.\n\n[https://en.wikipedia.org/wiki/Werejaguar](https://en.wikipedia.org/wiki/Werejaguar)\n\nNo, it's not a huge trout he just caught.\n\nIt's the same man that runs around in your dreams.  The one you believe you are exploring when you are \"lucid\".\n\nHe's brought it out into the real world.\n\nWe do that too.  I do it nightly, for hours.\n\nAnd in that \"double\", you can easily share dreams with others who aren't even asleep.\n\n\"Easily\" meaning, after shitloads of work to learn how.  It's not hard, but you have to learn how. Then it's \"easy\".\n\nMy witch friend Cholita was once in the kitchen, angry with me and cursing because I had come home.\n\nShe's totally crazy. \n\nI went back to my car in the driveway, only to find she was also outside.\n\nBut it's not unusual for her to be in 2 places at the same time.\n\nAnyway, I do what the Werejaguar beings in those jade figurines are doing almost nightly.\n\nSort of.  There's 500 more things to do, and that's low on the list.\n\nPlus it's kind of creepy.  And if you get too close to the double, you're likely to end up in his view of reality, with an open portal to another world on your wall.\n\nMine likes a shopping mall most.  I have no idea where it's located.\n\nSo if you want the real thing, read around.\n\nBut you've been confused by fake magic systems out there.  Profiteers.\n\nSo you have mountains to learn before you can understand the answer to your question.\n\nThe answer is yes.  You shifted dimensions.\n\nBut also no, that doesn't even make any sense.", "edited": 1665076618.0, "top_awarded_type": null, "downs": 0, "author_flair_css_class": null, "name": "t1_irayhsv", "is_submitter": false, "collapsed": false, "author_flair_richtext": [], "author_patreon_flair": false, "body_html": "&lt;div class=\"md\"&gt;&lt;p&gt;Wow, somewhat sincere.&lt;/p&gt;\n\n&lt;p&gt;You&amp;#39;ve been confused by the Lucid Dreaming folks, who toss me out if I try to teach them how to do waking dreaming.&lt;/p&gt;\n\n&lt;p&gt;You&amp;#39;d think they&amp;#39;d go NUTS to hear they can do lucid dreaming 3 hours every single day, with no risk of losing lucidity, and no risk of waking up.&lt;/p&gt;\n\n&lt;p&gt;But it only makes them so angry, they delete my posts.&lt;/p&gt;\n\n&lt;p&gt;Those are bad men in that subreddit, so I gave up on them.  God only knows what they&amp;#39;re really after.&lt;/p&gt;\n\n&lt;p&gt;It&amp;#39;s not exploration of dreams.&lt;/p&gt;\n\n&lt;p&gt;The pictures you see in here are mostly done fully awake, sober, eyes open, and kick the butt of anyone in the lucid dreaming forum, 100000 times over.&lt;/p&gt;\n\n&lt;p&gt;It&amp;#39;s real magic, from 10,000 year old proto-siberian shamanism.&lt;/p&gt;\n\n&lt;p&gt;It got handed down through the Olmecs.&lt;/p&gt;\n\n&lt;p&gt;Shapeshifting was their favorite dreaming hobby.&lt;/p&gt;\n\n&lt;p&gt;Is that a &amp;quot;shifted reality&amp;quot;?  When you turn into a Jaguar for real?&lt;/p&gt;\n\n&lt;p&gt;Beats me, but you seem to be polluted with fake system narratives so it&amp;#39;s not going to be easy for you to accept.&lt;/p&gt;\n\n&lt;p&gt;&lt;a href=\"https://www.google.com/search?q=olmec+shamanism+werejaguar&amp;amp;rlz=1C1CHZL_enUS706US706&amp;amp;source=lnms&amp;amp;tbm=isch&amp;amp;sa=X&amp;amp;ved=2ahUKEwiH-_-Yi8z6AhXoL0QIHXaXB80Q_AUoAXoECAEQAw&amp;amp;biw=1041&amp;amp;bih=774&amp;amp;dpr=1.25\"&gt;https://www.google.com/search?q=olmec+shamanism+werejaguar&amp;amp;rlz=1C1CHZL_enUS706US706&amp;amp;source=lnms&amp;amp;tbm=isch&amp;amp;sa=X&amp;amp;ved=2ahUKEwiH-_-Yi8z6AhXoL0QIHXaXB80Q_AUoAXoECAEQAw&amp;amp;biw=1041&amp;amp;bih=774&amp;amp;dpr=1.25&lt;/a&gt;&lt;/p&gt;\n\n&lt;p&gt;Hopefully the man holding himself in his dream form is at the top.&lt;/p&gt;\n\n&lt;p&gt;But if not, scroll down in this wikipedia entry and you&amp;#39;ll find him.&lt;/p&gt;\n\n&lt;p&gt;&lt;a href=\"https://en.wikipedia.org/wiki/Werejaguar\"&gt;https://en.wikipedia.org/wiki/Werejaguar&lt;/a&gt;&lt;/p&gt;\n\n&lt;p&gt;No, it&amp;#39;s not a huge trout he just caught.&lt;/p&gt;\n\n&lt;p&gt;It&amp;#39;s the same man that runs around in your dreams.  The one you believe you are exploring when you are &amp;quot;lucid&amp;quot;.&lt;/p&gt;\n\n&lt;p&gt;He&amp;#39;s brought it out into the real world.&lt;/p&gt;\n\n&lt;p&gt;We do that too.  I do it nightly, for hours.&lt;/p&gt;\n\n&lt;p&gt;And in that &amp;quot;double&amp;quot;, you can easily share dreams with others who aren&amp;#39;t even asleep.&lt;/p&gt;\n\n&lt;p&gt;&amp;quot;Easily&amp;quot; meaning, after shitloads of work to learn how.  It&amp;#39;s not hard, but you have to learn how. Then it&amp;#39;s &amp;quot;easy&amp;quot;.&lt;/p&gt;\n\n&lt;p&gt;My witch friend Cholita was once in the kitchen, angry with me and cursing because I had come home.&lt;/p&gt;\n\n&lt;p&gt;She&amp;#39;s totally crazy. &lt;/p&gt;\n\n&lt;p&gt;I went back to my car in the driveway, only to find she was also outside.&lt;/p&gt;\n\n&lt;p&gt;But it&amp;#39;s not unusual for her to be in 2 places at the same time.&lt;/p&gt;\n\n&lt;p&gt;Anyway, I do what the Werejaguar beings in those jade figurines are doing almost nightly.&lt;/p&gt;\n\n&lt;p&gt;Sort of.  There&amp;#39;s 500 more things to do, and that&amp;#39;s low on the list.&lt;/p&gt;\n\n&lt;p&gt;Plus it&amp;#39;s kind of creepy.  And if you get too close to the double, you&amp;#39;re likely to end up in his view of reality, with an open portal to another world on your wall.&lt;/p&gt;\n\n&lt;p&gt;Mine likes a shopping mall most.  I have no idea where it&amp;#39;s located.&lt;/p&gt;\n\n&lt;p&gt;So if you want the real thing, read around.&lt;/p&gt;\n\n&lt;p&gt;But you&amp;#39;ve been confused by fake magic systems out there.  Profiteers.&lt;/p&gt;\n\n&lt;p&gt;So you have mountains to learn before you can understand the answer to your question.&lt;/p&gt;\n\n&lt;p&gt;The answer is yes.  You shifted dimensions.&lt;/p&gt;\n\n&lt;p&gt;But also no, that doesn&amp;#39;t even make any sense.&lt;/p&gt;\n&lt;/div&gt;", "gildings": {}, "collapsed_reason": null, "distinguished": null, "associated_award": null, "stickied": false, "author_premium": false, "can_gild": false, "link_id": "t3_xx9b4l", "unrepliable_reason": null, "author_flair_text_color": null, "score_hidden": false, "permalink": "/r/castaneda/comments/xx9b4l/is_it_true_that_dreaming_in_a_dream_means_youre/irayhsv/", "subreddit_type": "public", "locked": false, "report_reasons": null, "created": 1665076371.0, "author_flair_text": null, "treatment_tags": [], "created_utc": 1665076371.0, "subreddit_name_prefixed": "r/castaneda", "controversiality": 0, "depth": 2, "author_flair_background_color": null, "collapsed_because_crowd_control": null, "mod_reports": [], "num_reports": null, "ups": 13}}], "before": null}}, "user_reports": [], "saved": false, "id": "irawxb6", "banned_at_utc": null, "mod_reason_title": null, "gilded": 0, "archived": false, "collapsed_reason_code": null, "no_follow": true, "author": "ermac_95", "can_mod_post": false, "created_utc": 1665075754.0, "send_replies": true, "parent_id": "t1_iravlbf", "score": 1, "author_fullname": "t2_qabab23e", "removal_reason": null, "approved_by": null, "mod_note": null, "all_awardings": [], "body": "I already know something along the lines about using LD to see other realities. But what I meant is I read someone say that if we realize we're dreaming within a dream subconsciously and without using LD techniques purposely, that it means that we're shifting to another dimension. I woke up from a bad dream and that's why I was asking, I don't want it to be true because I always had a feeling that dreaming within dreams had an important meaning.", "edited": 1665092722.0, "top_awarded_type": null, "author_flair_css_class": null, "name": "t1_irawxb6", "is_submitter": true, "downs": 0, "author_flair_richtext": [], "author_patreon_flair": false, "body_html": "&lt;div class=\"md\"&gt;&lt;p&gt;I already know something along the lines about using LD to see other realities. But what I meant is I read someone say that if we realize we&amp;#39;re dreaming within a dream subconsciously and without using LD techniques purposely, that it means that we&amp;#39;re shifting to another dimension. I woke up from a bad dream and that&amp;#39;s why I was asking, I don&amp;#39;t want it to be true because I always had a feeling that dreaming within dreams had an important meaning.&lt;/p&gt;\n&lt;/div&gt;", "gildings": {}, "collapsed_reason": null, "distinguished": null, "associated_award": null, "stickied": false, "author_premium": false, "can_gild": false, "link_id": "t3_xx9b4l", "unrepliable_reason": null, "author_flair_text_color": null, "score_hidden": false, "permalink": "/r/castaneda/comments/xx9b4l/is_it_true_that_dreaming_in_a_dream_means_youre/irawxb6/", "subreddit_type": "public", "locked": false, "report_reasons": null, "created": 1665075754.0, "author_flair_text": null, "treatment_tags": [], "collapsed": false, "subreddit_name_prefixed": "r/castaneda", "controversiality": 0, "depth": 1, "author_flair_background_color": null, "collapsed_because_crowd_control": null, "mod_reports": [], "num_reports": null, "ups": 1}}], "before": null}}, "user_reports": [], "saved": false, "id": "iravlbf", "banned_at_utc": null, "mod_reason_title": null, "gilded": 0, "archived": false, "collapsed_reason_code": null, "no_follow": false, "author": "danl999", "can_mod_post": false, "created_utc": 1665075245.0, "send_replies": true, "parent_id": "t3_xx9b4l", "score": 6, "author_fullname": "t2_yicrx32", "approved_by": null, "mod_note": null, "all_awardings": [], "collapsed": false, "body": "Everything you want to know is in here. Just scroll down and find a picture you like.\n\nAnd no one here has a monetary interest in helping people who won't make enough effort to learn on their own.\n\nYou came to a unique place, but didn't bother to look around.  Not sure what you hope to gain by that.\n\nMaybe you're used to places where everyone wants to steal your wallet at some point?  So they're eager to \"help\"?\n\nBut some of the new people likely don't mind giving it a try.\n\nIt's good practice for them.\n\nI expect what they'll learn is that you'll just leave, after trying to get a little attention.\n\nWe only come out ahead if someone puts in the hard work to learn.\n\nWe're trying to bring real magic back to the world, not create a new fake system to profit from.", "edited": 1665075462.0, "top_awarded_type": null, "author_flair_css_class": null, "name": "t1_iravlbf", "is_submitter": false, "downs": 0, "author_flair_richtext": [], "author_patreon_flair": false, "body_html": "&lt;div class=\"md\"&gt;&lt;p&gt;Everything you want to know is in here. Just scroll down and find a picture you like.&lt;/p&gt;\n\n&lt;p&gt;And no one here has a monetary interest in helping people who won&amp;#39;t make enough effort to learn on their own.&lt;/p&gt;\n\n&lt;p&gt;You came to a unique place, but didn&amp;#39;t bother to look around.  Not sure what you hope to gain by that.&lt;/p&gt;\n\n&lt;p&gt;Maybe you&amp;#39;re used to places where everyone wants to steal your wallet at some point?  So they&amp;#39;re eager to &amp;quot;help&amp;quot;?&lt;/p&gt;\n\n&lt;p&gt;But some of the new people likely don&amp;#39;t mind giving it a try.&lt;/p&gt;\n\n&lt;p&gt;It&amp;#39;s good practice for them.&lt;/p&gt;\n\n&lt;p&gt;I expect what they&amp;#39;ll learn is that you&amp;#39;ll just leave, after trying to get a little attention.&lt;/p&gt;\n\n&lt;p&gt;We only come out ahead if someone puts in the hard work to learn.&lt;/p&gt;\n\n&lt;p&gt;We&amp;#39;re trying to bring real magic back to the world, not create a new fake system to profit from.&lt;/p&gt;\n&lt;/div&gt;", "removal_reason": null, "collapsed_reason": null, "distinguished": null, "associated_award": null, "stickied": false, "author_premium": false, "can_gild": false, "gildings": {}, "unrepliable_reason": null, "author_flair_text_color": null, "score_hidden": false, "permalink": "/r/castaneda/comments/xx9b4l/is_it_true_that_dreaming_in_a_dream_means_youre/iravlbf/", "subreddit_type": "public", "locked": false, "report_reasons": null, "created": 1665075245.0, "author_flair_text": null, "treatment_tags": [], "link_id": "t3_xx9b4l", "subreddit_name_prefixed": "r/castaneda", "controversiality": 0, "depth": 0, "author_flair_background_color": null, "collapsed_because_crowd_control": null, "mod_reports": [], "num_reports": null, "ups": 6}}], "before": null}}]